alifTools/_version.py
alifTools/filters/__init__.py
alifTools/filters/clearPlaceholders.py
alifTools/filters/fontVersion.py
alifTools/filters/variableFeaConvertor.py
alifTools/sample/__init__.py
alifTools/sample/__main__.py
alifTools/shaping/__init__.py
alifTools/shaping/check.py
alifTools/shaping/update.py
aliftools-0.1.7.dist-info/licenses/LICENSE.txt
aliftools-0.1.7.dist-info/METADATA
aliftools-0.1.7.dist-info/WHEEL
aliftools-0.1.7.dist-info/entry_points.txt
aliftools-0.1.7.dist-info/top_level.txt
aliftools-0.1.7.dist-info/RECORD
