Metadata-Version: 2.4
Name: AlifTools
Version: 0.1.7
Summary: Helper tools for building Alif Type Foundry fonts
Author-email: Khaled Hosny <khaled@aliftype.com>
License: 
Project-URL: Repository, https://github.com/aliftype/tools
Project-URL: Issues, https://github.com/aliftype/tools/issues
Classifier: Environment :: Console
Classifier: Topic :: Text Processing :: Fonts
License-File: LICENSE.txt
Provides-Extra: test
Requires-Dist: pytest; extra == "test"
Requires-Dist: black; extra == "test"
Requires-Dist: isort; extra == "test"
Requires-Dist: flake8; extra == "test"
Requires-Dist: ufolib2; extra == "test"
Provides-Extra: shaping
Requires-Dist: pyyaml; extra == "shaping"
Requires-Dist: uharfbuzz>=0.52.0; extra == "shaping"
Provides-Extra: sample
Requires-Dist: blackrenderer; extra == "sample"
Requires-Dist: uharfbuzz>=0.43.0; extra == "sample"
Requires-Dist: fontTools[lxml]; extra == "sample"
Provides-Extra: filters
Requires-Dist: ufo2ft; extra == "filters"
Dynamic: license-file
